{"is_source_file": false, "format": "", "description": "", "external_files": [], "external_methods": [], "published": [], "classes": [], "methods": [], "calls": [], "search-terms": [], "state": 2, "file_id": 7, "knowledge_revision": 56, "git_revision": "a09b04736360fc00b2f8d055581e370bc647ccb5", "hash": "8a136cc54e22cda06a29a537ed5a5d29", "format-version": 4, "code-base-name": "frontend_react", "filename": "frontend_react/src/App.css", "revision_history": [{"56": "a09b04736360fc00b2f8d055581e370bc647ccb5"}]}